vectocore/__init__.py
vectocore/vectocore.py
vectocore-1.1.2.dist-info/licenses/LICENSE
vectocore-1.1.2.dist-info/METADATA
vectocore-1.1.2.dist-info/WHEEL
vectocore-1.1.2.dist-info/top_level.txt
vectocore-1.1.2.dist-info/RECORD
