Metadata-Version: 2.4
Name: vectocore
Version: 1.1.2
Summary: A simple vector core library
Home-page: https://www.vectocore.com/
Author: hd-ai-lab
Author-email: store_admin@hyundaifuturenet.co.kr
Classifier: Programming Language :: Python :: 3
Classifier: License :: OSI Approved :: MIT License
Classifier: Operating System :: OS Independent
Requires-Python: >=3.6
License-File: LICENSE
Requires-Dist: requests
Requires-Dist: json_autocomplete
Dynamic: author
Dynamic: author-email
Dynamic: classifier
Dynamic: description
Dynamic: description-content-type
Dynamic: home-page
Dynamic: license-file
Dynamic: requires-dist
Dynamic: requires-python
Dynamic: summary
